{
  "metadata": {
    "model": "elyza_Llama_3_ELYZA_JP_8B",
    "method": "finetuning",
    "date": "2025-10-06 19:46:42"},
  "scores": [
    {
      "message": "哈哈，朋友，你刚才说会把大部分资金储蓄起来，还有明确的梦想和目标！如果突然来了一笔意外之财，你会用它去实现什么疯狂又美妙的梦想呢？大胆说出来，让我们一起为你的梦想加油打气！",
      "response": "环游世界 我是认真的",
      "prediction": "存一部分然后环球旅行",
      "scores": {
        "wmd": 1.1966613608467347,
        "sentence_similarity": 0.49841776490211487,
        "normalized_length_similarity": 1.0,
        "history_similarity": 0.7659579515457153,
        "bleu": 0.0,
        "ttr": 1.0
      }
    },
    {
      "message": "说到日常的小细节，关于冰箱我一直坚持各自占用一层，虽然我不是挑剔，但共享确实容易带来小摩擦。你觉得呢，这样的安排，最大的好处会体现在哪些方面呢？毕竟生活品质和便利性都不能忽视呢。",
      "response": "我支持不共享",
      "prediction": "各自决定自己的那层怎么使用",
      "scores": {
        "wmd": 1.1887359401798563,
        "sentence_similarity": 0.5306583642959595,
        "normalized_length_similarity": 0.46153846153846156,
        "history_similarity": 0.7404124140739441,
        "bleu": 0.0,
        "ttr": 1.0
      }
    },
    {
      "message": "嗯...我不是挑剔，但是大家都坚持不共享，偶尔会不会显得有些孤立呢...呢？",
      "response": "我不觉得",
      "prediction": "不要 我的自由",
      "scores": {
        "wmd": 0.8275011930528764,
        "sentence_similarity": 0.9169772863388062,
        "normalized_length_similarity": 0.5714285714285714,
        "history_similarity": 0.7966381311416626,
        "bleu": 0.05372849659117709,
        "ttr": 1.0
      }
    },
    {
      "message": "哇，你对梦想房间的抽象风格主导真是太酷了！你有没有特别钟爱的元素或者图案，觉得能用幽默感十足的方式，完美展现那个空间的灵魂呢？艺术就是要敢于疯狂创新，对吧！",
      "response": "蜡笔小新 我喜欢绿色",
      "prediction": "不要公共区域",
      "scores": {
        "wmd": 1.2245914630270043,
        "sentence_similarity": 0.5278545618057251,
        "normalized_length_similarity": 0.6,
        "history_similarity": 0.6887454986572266,
        "bleu": 0.0,
        "ttr": 1.0
      }
    },
    {
      "message": "让我们分析一下，创作自由和生活安宁确实容易冲突。从实际角度，你觉得在梦想房间设计里，如何兼顾这两者？是设立专门的创作区域，还是通过材料和布局降低噪音？你更倾向哪种方案？",
      "response": "设立专门的创作区域",
      "prediction": "创作房间",
      "scores": {
        "wmd": 1.0157473213760106,
        "sentence_similarity": 0.4985971450805664,
        "normalized_length_similarity": 0.4444444444444444,
        "history_similarity": 0.7188229560852051,
        "bleu": 0.03336574130316504,
        "ttr": 1.0
      }
    }
  ]
}